vcstool2/__init__.py
vcstool2/crawler.py
vcstool2/executor.py
vcstool2/streams.py
vcstool2/util.py
vcstool2/clients/__init__.py
vcstool2/clients/git.py
vcstool2/clients/none.py
vcstool2/clients/vcs_base.py
vcstool2/commands/__init__.py
vcstool2/commands/branch.py
vcstool2/commands/command.py
vcstool2/commands/custom.py
vcstool2/commands/diff.py
vcstool2/commands/export.py
vcstool2/commands/help.py
vcstool2/commands/import_.py
vcstool2/commands/log.py
vcstool2/commands/pull.py
vcstool2/commands/push.py
vcstool2/commands/remotes.py
vcstool2/commands/rm.py
vcstool2/commands/status.py
vcstool2/commands/validate.py
vcstool2/commands/vcs.py
vcstool2-0.4.5.data/data/share/vcstool2-completion/vcs.bash
vcstool2-0.4.5.data/data/share/vcstool2-completion/vcs.fish
vcstool2-0.4.5.data/data/share/vcstool2-completion/vcs.tcsh
vcstool2-0.4.5.data/data/share/vcstool2-completion/vcs.zsh
vcstool2-0.4.5.dist-info/LICENSE
vcstool2-0.4.5.dist-info/METADATA
vcstool2-0.4.5.dist-info/WHEEL
vcstool2-0.4.5.dist-info/entry_points.txt
vcstool2-0.4.5.dist-info/top_level.txt
vcstool2-0.4.5.dist-info/RECORD
